odoo8_addon_sale_pricelist_discount-8.0.1.0.0-py2.7-nspkg.pth
odoo_addons/sale_pricelist_discount/__openerp__.py
odoo_addons/sale_pricelist_discount/__init__.py
odoo_addons/sale_pricelist_discount/README.rst
odoo_addons/sale_pricelist_discount/view/pricelist_view.xml
odoo_addons/sale_pricelist_discount/i18n/it.po
odoo_addons/sale_pricelist_discount/i18n/es.po
odoo_addons/sale_pricelist_discount/i18n/sl.po
odoo_addons/sale_pricelist_discount/i18n/de.po
odoo_addons/sale_pricelist_discount/i18n/fr.po
odoo_addons/sale_pricelist_discount/model/pricelist.py
odoo_addons/sale_pricelist_discount/model/sale.py
odoo_addons/sale_pricelist_discount/model/__init__.py
odoo8_addon_sale_pricelist_discount-8.0.1.0.0.dist-info/top_level.txt
odoo8_addon_sale_pricelist_discount-8.0.1.0.0.dist-info/WHEEL
odoo8_addon_sale_pricelist_discount-8.0.1.0.0.dist-info/RECORD
odoo8_addon_sale_pricelist_discount-8.0.1.0.0.dist-info/metadata.json
odoo8_addon_sale_pricelist_discount-8.0.1.0.0.dist-info/DESCRIPTION.rst
odoo8_addon_sale_pricelist_discount-8.0.1.0.0.dist-info/METADATA
odoo8_addon_sale_pricelist_discount-8.0.1.0.0.dist-info/namespace_packages.txt
