Metadata-Version: 2.0
Name: odoo8-addon-sale-pricelist-discount
Version: 8.0.1.0.0
Summary: Sale Pricelist Discount
Home-page: http://www.credativ.co.uk
Author: UNKNOWN
Author-email: UNKNOWN
License: UNKNOWN
Platform: UNKNOWN
Requires-Dist: odoo (<9.0a,>=8.0a)
Classifier: Programming Language :: Python :: 2.7
Classifier: Framework :: Odoo
